soccerpy/__init__.py
soccerpy/base.py
soccerpy/endpoint_manager.py
soccerpy/exceptions.py
soccerpy/requester.py
soccerpy/soccer.py
soccerpy/modules/__init__.py
soccerpy/modules/base_module.py
soccerpy/modules/search_module.py
soccerpy/modules/Competition/__init__.py
soccerpy/modules/Competition/base_competition.py
soccerpy/modules/Competition/competition.py
soccerpy/modules/Competition/competition_fixtures.py
soccerpy/modules/Competition/competition_league_table.py
soccerpy/modules/Competition/competition_specific.py
soccerpy/modules/Competition/competition_teams.py
soccerpy/modules/Competition/competitions_all.py
soccerpy/modules/Fixture/__init__.py
soccerpy/modules/Fixture/base_fixture.py
soccerpy/modules/Fixture/fixture.py
soccerpy/modules/Fixture/fixtures_all.py
soccerpy/modules/Fixture/fixtures_specific.py
soccerpy/modules/Fundamentals/__init__.py
soccerpy/modules/Fundamentals/base_fundamental.py
soccerpy/modules/Fundamentals/competitions.py
soccerpy/modules/Fundamentals/fixtures.py
soccerpy/modules/Fundamentals/head2head.py
soccerpy/modules/Fundamentals/master.py
soccerpy/modules/Fundamentals/players.py
soccerpy/modules/Fundamentals/searchable.py
soccerpy/modules/Fundamentals/standing.py
soccerpy/modules/Fundamentals/teams.py
soccerpy/modules/Fundamentals/links/__init__.py
soccerpy/modules/Fundamentals/links/base_links.py
soccerpy/modules/Fundamentals/links/competition_links.py
soccerpy/modules/Fundamentals/links/fixture_links.py
soccerpy/modules/Fundamentals/links/team_links.py
soccerpy/modules/Team/__init__.py
soccerpy/modules/Team/base_team.py
soccerpy/modules/Team/team.py
soccerpy/modules/Team/team_fixtures.py
soccerpy/modules/Team/team_players.py
soccerpy/modules/Team/team_specific.py
soccerpy-0.1.0.dist-info/DESCRIPTION.rst
soccerpy-0.1.0.dist-info/METADATA
soccerpy-0.1.0.dist-info/RECORD
soccerpy-0.1.0.dist-info/WHEEL
soccerpy-0.1.0.dist-info/metadata.json
soccerpy-0.1.0.dist-info/top_level.txt
tests/__init__.py
tests/test_soccer.py
tests/modules/__init__.py
tests/modules/test_competition.py
tests/modules/test_fixture.py
tests/modules/test_team.py
tests/modules/utils.py
