Metadata-Version: 2.0
Name: soccerpy
Version: 0.1.0
Summary: A python wrapper for API Football-data (api.football-data.org)
Home-page: https://github.com/slapbot/newsapi
Author: Ujjwal Gupta
Author-email: ugupta41@gmail.com
License: MIT
Requires-Dist: requests
